{
  "clients": [
    {
      "id": 12345,
      "name": "Agustin Barbero",
      "email": "nicolasmartincossi@gmail.com",
      "phone": "",
      "adress": "Leopoldo Lugones 443",
      "CUIT": "20444444446",
      "extras": "Jefecitoo"
    },
    {
      "id": 5462,
      "name": "ramiro isa",
      "email": "ram@isa",
      "phone": "2011111111",
      "adress": "Leopoldo Lugones 443",
      "CUIT": "11111",
      "extras": "asdada"
    }
  ],
  "invoices": [
    {
      "id": 12345,
      "clientId": 1,
      "date": "2023-07-10",
      "delivery_address": "Leopoldo Lugones 443",
      "items": [
        {
          "id": 1,
          "name": "Volquete",
          "item_number": "#80",
          "delivery_date": 0,
          "withdraw_date": 0,
          "total_periods": 0,
          "period_price": 10000
        }
      ]
    },
    {
      "items": [
        {
          "id": 1,
          "name": "Obrador",
          "item_number": "100",
          "delivery_date": "2023-07-21",
          "withdraw_date": 0,
          "total_periods": 0,
          "period_price": 15000
        },
        {
          "id": 2,
          "name": "Volquete",
          "item_number": "22",
          "delivery_date": "2023-07-21",
          "withdraw_date": 0,
          "total_periods": 0,
          "period_price": 10000
        }
      ],
      "id": 9324,
      "clientId": "12345",
      "date": "2023-07-20",
      "delivery_address": "Witcomb 5500"
    },
    {
      "items": [
        {
          "id": 2,
          "name": "Volquete",
          "item_number": "12",
          "delivery_date": "0012-01-12",
          "withdraw_date": 0,
          "total_periods": 0,
          "period_price": 10000
        }
      ],
      "id": 3660,
      "clientId": "12345",
      "date": "1332-03-12",
      "delivery_address": "pollo"
    }
  ]
}